clixdev/__init__.py
clixdev/commands.py
clixdev/terminal.py
clixdev/trace.py
clixdev/kit/__init__.py
clixdev/kit/middleware.py
clixdev-0.3.9.1.dist-info/LICENSE
clixdev-0.3.9.1.dist-info/METADATA
clixdev-0.3.9.1.dist-info/WHEEL
clixdev-0.3.9.1.dist-info/entry_points.txt
clixdev-0.3.9.1.dist-info/top_level.txt
clixdev-0.3.9.1.dist-info/RECORD
