Metadata-Version: 2.1
Name: clixdev
Version: 0.3.9.1
Summary: https://clix.dev command line tool.
Author-email: Eris Verne <erisverne7@gmail.com>
License: MIT License        
Project-URL: Homepage, https://clix.dev
Classifier: Programming Language :: Python :: 3
Classifier: License :: OSI Approved :: MIT License
Classifier: Operating System :: OS Independent
Requires-Python: >=3.8
License-File: LICENSE
Requires-Dist: requests
Requires-Dist: termcolor
Requires-Dist: Django
Requires-Dist: Pillow
Requires-Dist: sqlparse
Requires-Dist: urllib3
Requires-Dist: certifi
Requires-Dist: asgiref
Requires-Dist: charset-normalizer
Requires-Dist: idna
